{
  "": "",
  "About us": "About us",
  "Age": "Age",
  "All articles": "All articles",
  "Article not found": "Article not found",
  "At": "At",
  "Auth Form ": "Auth Form ",
  "Avatar": "Avatar",
  "Back": "Back",
  "By": "By",
  "Cancel": "Cancel",
  "City": "City",
  "Comment": "Comment",
  "Comments": "Comments",
  "Country": "Country",
  "Currency": "Currency",
  "Economics": "Economics",
  "Edit": "Edit",
  "First Name": "First Name",
  "First and last name are required": "First and last name are required",
  "Form Auth": "Form Auth",
  "IT": "IT",
  "Incorrect age": "Incorrect age",
  "Invalid region": "Invalid region",
  "Language": "Language",
  "Last Name": "Last Name",
  "Login": "Login",
  "Logout": "Logout",
  "Main page": "Main page",
  "Modal": "Modal",
  "No comments": "No comments",
  "No data": "No data",
  "PROFILE PAGE": "PROFILE PAGE",
  "Page not found": "Page not found",
  "Password": "Password",
  "Please refresh the page": "Please refresh the page",
  "Profile": "Profile",
  "Read more": {
    "": {
      "": {
        "": ""
      }
    }
  },
  "Refresh page": "Refresh page",
  "Save": "Save",
  "Science": "Science",
  "Search": "Search",
  "Send": "Send",
  "Server error": "Server error",
  "Short Language": "Short Language",
  "Sort By": "Sort By",
  "There was an unexpected error": "There was an unexpected error",
  "Username": "Username",
  "ascending": "ascending",
  "date of creation": "date of creation",
  "decrement": "decrement",
  "descending": "descending",
  "error": "error",
  "increment": "increment",
  "throw error": "throw error",
  "title": "title",
  "toggle": "toggle",
  "views": "views"
}
